artiik/__init__.py
artiik-0.1.0.dist-info/licenses/LICENSE.md
context_manager/__init__.py
context_manager/core/__init__.py
context_manager/core/config.py
context_manager/core/orchestrator.py
context_manager/examples/__init__.py
context_manager/examples/agent_example.py
context_manager/llm/__init__.py
context_manager/llm/adapters.py
context_manager/llm/embeddings.py
context_manager/memory/__init__.py
context_manager/memory/long_term.py
context_manager/memory/short_term.py
context_manager/memory/summarizer.py
context_manager/utils/__init__.py
context_manager/utils/token_counter.py
artiik-0.1.0.dist-info/METADATA
artiik-0.1.0.dist-info/WHEEL
artiik-0.1.0.dist-info/entry_points.txt
artiik-0.1.0.dist-info/top_level.txt
artiik-0.1.0.dist-info/RECORD
